hybrid_shoot/__init__.py
hybrid_shoot/_hybrid_shoot.cp311-win_amd64.pyd
hybrid_shoot/gym_wrapper.py
hybrid_shoot/pettingzoo_wrapper.py
hybrid_shoot/version.py
hybrid_shoot-0.1.6.dist-info/METADATA
hybrid_shoot-0.1.6.dist-info/WHEEL
hybrid_shoot-0.1.6.dist-info/RECORD
