Metadata-Version: 2.1
Name: hybrid_shoot
Version: 0.1.6
Summary: A custom RL environment with C++ backend and Gymnasium wrapper.
Author: Your Name
License: MIT
Project-URL: Homepage, https://github.com/you/my-custom-env
Requires-Python: >=3.9
Requires-Dist: gymnasium>=0.29
Requires-Dist: numpy
Requires-Dist: pygame>=2.1.0
